purebox/__init__.py
purebox/__main__.py
purebox/purebox.py
purebox-0.1.1.dist-info/METADATA
purebox-0.1.1.dist-info/WHEEL
purebox-0.1.1.dist-info/entry_points.txt
purebox-0.1.1.dist-info/licenses/LICENSE
purebox-0.1.1.dist-info/RECORD
