Metadata-Version: 2.1
Name: purebox
Version: 0.1.1
Summary: Utility to draw rectangles on programs using Xlib to get x, y, width, height coordinates
Project-URL: Homepage, https://github.com/4ndrs/PureBox
Project-URL: Bug Tracker, https://github.com/4ndrs/PureBox/issues
Author-email: 4ndrs <andres.degozaru@gmail.com>
License: MIT License
Classifier: Environment :: X11 Applications
Classifier: License :: OSI Approved :: MIT License
Classifier: Operating System :: POSIX :: Linux
Classifier: Programming Language :: Python :: 3
Classifier: Topic :: Software Development :: Libraries :: Python Modules
Requires-Python: >=3.10
Requires-Dist: python-xlib==0.31
